tokonomics/__init__.py
tokonomics/core.py
tokonomics/data_models.py
tokonomics/helpers.py
tokonomics/log.py
tokonomics/model_discovery/__init__.py
tokonomics/model_discovery/anthropic_provider/__init__.py
tokonomics/model_discovery/anthropic_provider/provider.py
tokonomics/model_discovery/base.py
tokonomics/model_discovery/cerebras_provider/__init__.py
tokonomics/model_discovery/cerebras_provider/provider.py
tokonomics/model_discovery/claude_code_provider/__init__.py
tokonomics/model_discovery/claude_code_provider/provider.py
tokonomics/model_discovery/cohere_provider/__init__.py
tokonomics/model_discovery/cohere_provider/provider.py
tokonomics/model_discovery/comet_provider/__init__.py
tokonomics/model_discovery/comet_provider/provider.py
tokonomics/model_discovery/copilot_provider/__init__.py
tokonomics/model_discovery/copilot_provider/provider.py
tokonomics/model_discovery/copilot_provider/token_manager.py
tokonomics/model_discovery/deepseek_provider/__init__.py
tokonomics/model_discovery/deepseek_provider/provider.py
tokonomics/model_discovery/gemini_provider/__init__.py
tokonomics/model_discovery/gemini_provider/provider.py
tokonomics/model_discovery/github_provider/__init__.py
tokonomics/model_discovery/github_provider/provider.py
tokonomics/model_discovery/groq_provider/__init__.py
tokonomics/model_discovery/groq_provider/provider.py
tokonomics/model_discovery/mistral_provider/__init__.py
tokonomics/model_discovery/mistral_provider/provider.py
tokonomics/model_discovery/model_info.py
tokonomics/model_discovery/modelsdev_provider/__init__.py
tokonomics/model_discovery/modelsdev_provider/provider.py
tokonomics/model_discovery/novita_provider/__init__.py
tokonomics/model_discovery/novita_provider/provider.py
tokonomics/model_discovery/ollama_provider/__init__.py
tokonomics/model_discovery/ollama_provider/provider.py
tokonomics/model_discovery/openai_provider/__init__.py
tokonomics/model_discovery/openai_provider/provider.py
tokonomics-1.2.17.dist-info/licenses/LICENSE
tokonomics-1.2.17.dist-info/WHEEL
tokonomics-1.2.17.dist-info/METADATA
tokonomics-1.2.17.dist-info/RECORD
