Metadata-Version: 2.4
Name: tokonomics
Version: 1.2.17
Summary: Calcuate costs for LLM Usage based on token count
Keywords: 
Author: Philipp Temminghoff
Author-email: Philipp Temminghoff <philipptemminghoff@googlemail.com>
License-Expression: MIT
License-File: LICENSE
Classifier: Development Status :: 4 - Beta
Classifier: Framework :: Pydantic
Classifier: Framework :: Pydantic :: 2
Classifier: Intended Audience :: Developers
Classifier: Operating System :: OS Independent
Classifier: Programming Language :: Python :: 3
Classifier: Programming Language :: Python :: 3 :: Only
Classifier: Programming Language :: Python :: 3.12
Classifier: Programming Language :: Python :: 3.13
Classifier: Programming Language :: Python :: 3.14
Classifier: Topic :: Documentation
Classifier: Topic :: Software Development
Classifier: Topic :: Utilities
Classifier: Typing :: Typed
Requires-Dist: anyenv[httpx]>=0.3.2
Requires-Dist: httpx>=0.27.2
Requires-Dist: platformdirs>=4.3.6
Requires-Dist: pydantic
Requires-Dist: schemez
Requires-Dist: tiktoken ; extra == 'tiktoken'
Requires-Python: >=3.13
Project-URL: Code coverage, https://app.codecov.io/gh/phil65/tokonomics
Project-URL: Discussions, https://github.com/phil65/tokonomics/discussions
Project-URL: Documentation, https://phil65.github.io/tokonomics/
Project-URL: Issues, https://github.com/phil65/tokonomics/issues
Project-URL: Source, https://github.com/phil65/tokonomics
Provides-Extra: tiktoken
